zotero2readwise/__init__.py
zotero2readwise/exception.py
zotero2readwise/helper.py
zotero2readwise/readwise.py
zotero2readwise/run.py
zotero2readwise/test.py
zotero2readwise/zotero.py
zotero2readwise/zt2rw.py
zotero2readwise-1.3.0.dist-info/METADATA
zotero2readwise-1.3.0.dist-info/WHEEL
zotero2readwise-1.3.0.dist-info/entry_points.txt
zotero2readwise-1.3.0.dist-info/licenses/LICENSE
zotero2readwise-1.3.0.dist-info/RECORD
