Metadata-Version: 2.4
Name: zotero2readwise
Version: 1.3.0
Summary: Export your Zotero annotations and notes to Readwise
Project-URL: Homepage, https://github.com/e-alizadeh/Zotero2Readwise
Project-URL: Repository, https://github.com/e-alizadeh/Zotero2Readwise
Project-URL: Documentation, https://github.com/e-alizadeh/Zotero2Readwise
Author-email: ealizadeh <hello@ealizadeh.com>
License: MIT
License-File: LICENSE
Keywords: Readwise,Zotero
Classifier: Development Status :: 3 - Alpha
Classifier: License :: OSI Approved :: MIT License
Classifier: Programming Language :: Python :: 3.12
Classifier: Programming Language :: Python :: 3.13
Classifier: Programming Language :: Python :: Implementation :: PyPy
Classifier: Topic :: Software Development :: Build Tools
Classifier: Topic :: Software Development :: Libraries :: Python Modules
Classifier: Topic :: Utilities
Requires-Python: >=3.12
Requires-Dist: python-dotenv<1.1.0
Requires-Dist: pyzotero>=1.4.26
Requires-Dist: requests>=2.26.0
Provides-Extra: dev
Requires-Dist: ipdb>=0.13.13; extra == 'dev'
Requires-Dist: ipython>=8.10.0; extra == 'dev'
Requires-Dist: pre-commit>=3.5.0; extra == 'dev'
Requires-Dist: pytest-cov>=4.1.0; extra == 'dev'
Requires-Dist: pytest-mock>=3.12.0; extra == 'dev'
Requires-Dist: pytest>=8.0.0; extra == 'dev'
